peelee/__init__.py
peelee/__main__.py
peelee/color.py
peelee/color_utils.py
peelee/peelee.py
peelee/random_color.py
peelee-0.2.55.dist-info/METADATA
peelee-0.2.55.dist-info/WHEEL
peelee-0.2.55.dist-info/licenses/LICENSE
peelee-0.2.55.dist-info/RECORD
