Metadata-Version: 2.4
Name: peelee
Version: 0.2.55
Summary: A python library to create countless palettes.
License: MIT
License-File: LICENSE
Author: Bruce Wen
Author-email: wenijinew@gmail.com
Requires-Python: >=3.11,<4.0
Classifier: License :: OSI Approved :: MIT License
Classifier: Programming Language :: Python :: 3
Classifier: Programming Language :: Python :: 3.11
Classifier: Programming Language :: Python :: 3.12
Classifier: Programming Language :: Python :: 3.13
Classifier: Programming Language :: Python :: 3.14
Requires-Dist: loguru (>=0.7.3,<0.8.0)
